{
	"id": 319,
	"name": "wtf challenge",
	"author": "Hex",
	"creators": [
		"Hex"
	],
	"verifier": "Hex",
	"verification": "",
	"percentToQualify": 100,
	"password": "-",
	"records": [
    {
			"user": "ItzPickles",
			"link": "",
			"percent": 100,
			"hz": 240
		},
    {
			"user": "WhirlPloof",
			"link": "",
			"percent": 100,
			"hz": 240
		},
    {
			"user": "Skoe",
			"link": "",
			"percent": 100,
			"hz": 240
		},
    {
			"user": "Furrious",
			"link": "https://www.youtube.com/watch?v=25cFLgV-KVg&ab_channel=Furrious%5BGD%5D",
			"percent": 100,
			"hz": 240
		},
    {
			"user": "Kubix",
			"link": "",
			"percent": 100,
			"hz": 165
		}
  ]
}
